{"name":"Septuagint-dev","tagline":"Machine-corrected version of Henry Barclay Swetes Septuagint.","body":"#Welcome to **septuagint-dev**!\r\n\r\n##About\r\nThis repository hosts digital versions of Henry Barclay Swetes _Septuagint_.\r\n\r\nThese XML files were produced by data entry company [Digital Divide Data](http://www.digitaldividedata.org/) (DDD), who corrected and encoded hOCR output generated by [Bruce Robertson](https://github.com/brobertson) in accordance with the latest [EpiDoc](http://sourceforge.net/p/epidoc/wiki/Home/) standards.\r\nWhile adequate, more can and should be done to improve the XML (the -dev(elopment) suffix indicates the repository is open to improvement).\r\n\r\n##Volumes\r\n\r\n* [Vol. I](https://github.com/OpenGreekAndLatin/septuagint-dev/blob/master/old_testament_1901_vol1.xml): _Septuagint. Genesis - IV Kings_ (1901), ed. Henry Barclay Swete.\r\n* [Vol. II]\r\n* [Vol. III]","google":"","note":"Don't delete this file! It's used internally to help with page regeneration."}